zmp_openapi_models/__init__.py
zmp_openapi_models/alerts/__init__.py
zmp_openapi_models/alerts/alert_model.py
zmp_openapi_models/alerts/auth_model.py
zmp_openapi_models/alerts/channel_model.py
zmp_openapi_models/alerts/integration_model.py
zmp_openapi_models/alerts/kakaotalk_model.py
zmp_openapi_models/alerts/result_model.py
zmp_openapi_models/alerts/silence_model.py
zmp_openapi_models/alerts/user_notification_settings.py
zmp_openapi_models/utils/time_utils.py
zmp_openapi_models-0.1.1.dist-info/METADATA
zmp_openapi_models-0.1.1.dist-info/WHEEL
zmp_openapi_models-0.1.1.dist-info/RECORD
