Metadata-Version: 2.3
Name: zmp-openapi-models
Version: 0.1.1
Summary: The collection of the openapi models of the cloud zmp
Author: Kilsoo Kang
Author-email: kilsoo75@gmail.com
Requires-Python: >=3.11, <4.0
Classifier: Programming Language :: Python :: 3
Classifier: Programming Language :: Python :: 3.11
Classifier: Programming Language :: Python :: 3.12
Classifier: Programming Language :: Python :: 3.13
Requires-Dist: pydantic (>=2.10.6,<3.0.0)
